phish_detector/__init__.py
phish_detector-1.0.0.dist-info/METADATA
phish_detector-1.0.0.dist-info/WHEEL
phish_detector-1.0.0.dist-info/top_level.txt
phish_detector-1.0.0.dist-info/RECORD
