Metadata-Version: 2.1
Name: phish-detector
Version: 1.0.0
Summary: A discord webhook client written in Python.
Home-page: https://github.com/ElijahGives/phish-detector
Author: ElijahGives
Author-email: elijahgives13@gmail.com
License: LICENSE
Platform: UNKNOWN
Classifier: Programming Language :: Python :: 3
Classifier: License :: OSI Approved :: GNU General Public License v3 or later (GPLv3+)
Classifier: Operating System :: OS Independent
